sd_mecha/__init__.py
sd_mecha/conversion.py
sd_mecha/helpers.py
sd_mecha/merge_method_wrappers.py
sd_mecha/merging.py
sd_mecha/recipe_nodes.py
sd_mecha/serialization.py
sd_mecha/streaming.py
sd_mecha/typing_.py
sd_mecha/extensions/__init__.py
sd_mecha/extensions/merge_methods.py
sd_mecha/extensions/merge_spaces.py
sd_mecha/extensions/model_configs.py
sd_mecha/extensions/model_formats.py
sd_mecha/extensions/builtin/lycoris.py
sd_mecha/extensions/builtin/merge_methods/__init__.py
sd_mecha/extensions/builtin/merge_methods/clamp.py
sd_mecha/extensions/builtin/merge_methods/cosine.py
sd_mecha/extensions/builtin/merge_methods/crossover.py
sd_mecha/extensions/builtin/merge_methods/ema.py
sd_mecha/extensions/builtin/merge_methods/linear.py
sd_mecha/extensions/builtin/merge_methods/logistics.py
sd_mecha/extensions/builtin/merge_methods/slicing.py
sd_mecha/extensions/builtin/merge_methods/svd.py
sd_mecha/extensions/builtin/merge_methods/ties_sum.py
sd_mecha/extensions/builtin/model_configs/__init__.py
sd_mecha/extensions/builtin/model_configs/convert_flux.py
sd_mecha/extensions/builtin/model_configs/convert_huggingface_sd_vae_to_original.py
sd_mecha/extensions/builtin/model_configs/convert_sd1_blocks.py
sd_mecha/extensions/builtin/model_configs/convert_sd1_kohya_to_original.py
sd_mecha/extensions/builtin/model_configs/convert_sdxl_blocks.py
sd_mecha/extensions/builtin/model_configs/convert_sdxl_diffusers_unet_to_original.py
sd_mecha/extensions/builtin/model_configs/convert_sdxl_kohya_to_original.py
sd_mecha/extensions/builtin/model_configs/flux-flux.yaml
sd_mecha/extensions/builtin/model_configs/flux-flux_diffuser_only.yaml
sd_mecha/extensions/builtin/model_configs/sd1-kohya.yaml
sd_mecha/extensions/builtin/model_configs/sd1-ldm.yaml
sd_mecha/extensions/builtin/model_configs/sd1-supermerger_blocks.yaml
sd_mecha/extensions/builtin/model_configs/sd3-comfyui.yaml
sd_mecha/extensions/builtin/model_configs/sdxl-diffusers_unet_only.yaml
sd_mecha-1.0.13.dist-info/licenses/LICENSE
sd_mecha-1.0.13.dist-info/licenses/LICENSE-pytorch.txt
sd_mecha-1.0.13.dist-info/licenses/LICENSE-safetensors.txt
sd_mecha-1.0.13.dist-info/METADATA
sd_mecha-1.0.13.dist-info/WHEEL
sd_mecha-1.0.13.dist-info/top_level.txt
sd_mecha-1.0.13.dist-info/RECORD
