Metadata-Version: 2.4
Name: sd-mecha
Version: 1.0.13
Summary: State dict recipe merger
Author: ljleb
Project-URL: Homepage, https://github.com/ljleb/sd-mecha
Project-URL: Issues, https://github.com/ljleb/sd-mecha/issues
Classifier: License :: OSI Approved :: MIT License
Classifier: Programming Language :: Python :: 3
Requires-Python: >=3.10
License-File: LICENSE
License-File: LICENSE-pytorch.txt
License-File: LICENSE-safetensors.txt
Requires-Dist: click>=8.1.7
Requires-Dist: numpy>=1.26.0
Requires-Dist: torch>=2.1.0
Requires-Dist: scipy>=1.14.0
Requires-Dist: safetensors>=0.4.2
Requires-Dist: tqdm>=4.66.2
Requires-Dist: fuzzywuzzy>=0.18.0
Requires-Dist: python-Levenshtein
Requires-Dist: PyYAML>=6.0.1
Dynamic: license-file
